django_silhouette-0.0.3.dist-info/DESCRIPTION.rst
django_silhouette-0.0.3.dist-info/METADATA
django_silhouette-0.0.3.dist-info/RECORD
django_silhouette-0.0.3.dist-info/WHEEL
django_silhouette-0.0.3.dist-info/metadata.json
django_silhouette-0.0.3.dist-info/top_level.txt
silhouette/__init__.py
silhouette/apps.py
silhouette/loaders.py
silhouette/models.py
silhouette/settings.py
silhouette/utils.py
silhouette/templates/silhouette/base/fields/errors.html
silhouette/templates/silhouette/base/fields/field.html
silhouette/templates/silhouette/base/fields/help_text.html
silhouette/templates/silhouette/base/forms/controls.html
silhouette/templates/silhouette/base/forms/errors.html
silhouette/templates/silhouette/base/forms/fields.html
silhouette/templates/silhouette/base/forms/form.html
silhouette/templates/silhouette/base/forms/media.html
silhouette/templates/silhouette/base/formsets/errors.html
silhouette/templates/silhouette/base/formsets/formset.html
silhouette/templatetags/__init__.py
silhouette/templatetags/silhouette_filters.py
silhouette/templatetags/silhouette_tags.py
tests/__init__.py
tests/manage.py
tests/pods_utils.py
tests/settings.py
tests/test_filters.py
tests/test_loaders.py
tests/test_tags.py
tests/test_utils.py
tests/mock/__init__.py
tests/mock/forms.py
tests/mock/tags.py
